[{"line":1,"elements":[{"start_timestamp":"2025-11-06T18:39:28.527Z","before":[{"result":{"duration":2688000,"status":"passed"},"match":{"location":"steps.Hooks.setUp()"}}],"line":21,"name":"login ParaBank","description":"","id":"parabank;login-parabank","after":[{"result":{"duration":193000,"status":"passed"},"match":{"location":"steps.Hooks.tearDown()"}}],"type":"scenario","keyword":"Scenario","steps":[{"result":{"duration":737550000,"status":"passed"},"line":22,"name":"Open ParaBank application","match":{"location":"steps.BankLogin.open_para_bank_application()"},"keyword":"Given "},{"result":{"duration":4425599000,"status":"passed"},"line":23,"name":"Login to application","match":{"location":"steps.BankLogin.login_to_application()"},"keyword":"When "},{"result":{"duration":503280000,"status":"passed"},"line":24,"name":"Verify user successfully logged into application","match":{"location":"steps.BankLogin.verify_user_successfully_logged_into_application()"},"keyword":"Then "}],"tags":[{"name":"@Bank"}]}],"name":"ParaBank","description":"","id":"parabank","keyword":"Feature","uri":"file:src/test/resources/features/bank_registration.feature","tags":[]}]